streamlit_scroll_to_top/__init__.py
streamlit_scroll_to_top/frontend/build/asset-manifest.json
streamlit_scroll_to_top/frontend/build/bootstrap.min.css
streamlit_scroll_to_top/frontend/build/index.html
streamlit_scroll_to_top/frontend/build/static/js/main.2168ba39.js
streamlit_scroll_to_top/frontend/build/static/js/main.2168ba39.js.LICENSE.txt
streamlit_scroll_to_top/frontend/build/static/js/main.2168ba39.js.map
streamlit_scroll_to_top/frontend/build/static/js/main.2f9005eb.js
streamlit_scroll_to_top/frontend/build/static/js/main.2f9005eb.js.LICENSE.txt
streamlit_scroll_to_top/frontend/build/static/js/main.2f9005eb.js.map
streamlit_scroll_to_top/frontend/build/static/js/main.82088e4e.js
streamlit_scroll_to_top/frontend/build/static/js/main.82088e4e.js.LICENSE.txt
streamlit_scroll_to_top/frontend/build/static/js/main.82088e4e.js.map
streamlit_scroll_to_top/frontend/build/static/js/main.96bc179f.js
streamlit_scroll_to_top/frontend/build/static/js/main.96bc179f.js.LICENSE.txt
streamlit_scroll_to_top/frontend/build/static/js/main.96bc179f.js.map
streamlit_scroll_to_top/frontend/build/static/js/main.a4296ee9.js
streamlit_scroll_to_top/frontend/build/static/js/main.a4296ee9.js.LICENSE.txt
streamlit_scroll_to_top/frontend/build/static/js/main.a4296ee9.js.map
streamlit_scroll_to_top/frontend/build/static/js/main.a6dd0420.js
streamlit_scroll_to_top/frontend/build/static/js/main.a6dd0420.js.LICENSE.txt
streamlit_scroll_to_top/frontend/build/static/js/main.a6dd0420.js.map
streamlit_scroll_to_top-0.0.4.dist-info/LICENSE
streamlit_scroll_to_top-0.0.4.dist-info/METADATA
streamlit_scroll_to_top-0.0.4.dist-info/WHEEL
streamlit_scroll_to_top-0.0.4.dist-info/top_level.txt
streamlit_scroll_to_top-0.0.4.dist-info/RECORD
