Metadata-Version: 2.1
Name: streamlit-scroll-to-top
Version: 0.0.4
Summary: A Streamlit custom component to allow one click scrolling to different locations on your page
Home-page: https://github.com/bowespublishing/streamlit-scroll-to-top
Author: Bowes Publishing
Author-email: bowespublishing@gmail.com
Requires-Python: >=3.6
License-File: LICENSE
Requires-Dist: streamlit >=0.63
